examples/__init__.py
examples/gs0_hello_world.py
examples/l0_routing/__init__.py
examples/l0_routing/l0_main.py
examples/l1_balancing/__init__.py
examples/l1_balancing/l1_main.py
examples/l2_distributed/__init__.py
examples/l2_distributed/l2_configs.py
examples/l2_distributed/l2_main.py
examples/l2_distributed/l2_net.py
tethys/VERSION
tethys/__init__.py
tethys/apps/__init__.py
tethys/apps/base.py
tethys/apps/worker/__init__.py
tethys/apps/worker/app.py
tethys/apps/worker/configurator.py
tethys/apps/worker/settings.py
tethys/bin/__init__.py
tethys/bin/cli.py
tethys/bin/tethys
tethys/core/__init__.py
tethys/core/exceptions.py
tethys/core/networks/__init__.py
tethys/core/networks/network_base.py
tethys/core/networks/network_zero.py
tethys/core/nodes/__init__.py
tethys/core/nodes/node_base.py
tethys/core/nodes/node_zero.py
tethys/core/nodes/operators/__init__.py
tethys/core/nodes/operators/operator_base.py
tethys/core/nodes/operators/balancing/__init__.py
tethys/core/nodes/operators/balancing/operator_round_robin.py
tethys/core/nodes/operators/bash/__init__.py
tethys/core/nodes/operators/bash/operator_bash_per_packet.py
tethys/core/nodes/operators/files/__init__.py
tethys/core/nodes/operators/files/operator_read_file.py
tethys/core/nodes/operators/python/__init__.py
tethys/core/nodes/operators/python/operator_dummy.py
tethys/core/nodes/operators/python/operator_python_fn.py
tethys/core/pipes/__init__.py
tethys/core/pipes/pipe_base.py
tethys/core/pipes/pipe_zero.py
tethys/core/pipes/filters/__init__.py
tethys/core/pipes/filters/filter_base.py
tethys/core/pipes/filters/filter_composite.py
tethys/core/pipes/filters/filter_function.py
tethys/core/pipes/filters/filter_json_content.py
tethys/core/pipes/filters/filter_regex_str.py
tethys/core/regobjs/__init__.py
tethys/core/regobjs/regobj_base.py
tethys/core/regobjs/regobj_zero.py
tethys/core/regobjs/repositories/__init__.py
tethys/core/regobjs/repositories/repo_base.py
tethys/core/regobjs/repositories/repo_json_file.py
tethys-0.0.0.dist-info/LICENSE
tethys-0.0.0.dist-info/LICENSE.tpl
tethys-0.0.0.dist-info/METADATA
tethys-0.0.0.dist-info/WHEEL
tethys-0.0.0.dist-info/top_level.txt
tethys-0.0.0.dist-info/RECORD
